{
    "bounds": {
        "minlat": 46.5043006,
        "minlon": 6.5838681,
        "maxlat": 46.6025773,
        "maxlon": 6.7208137
    },
    "id": 1685018,
    "tags": {
        "admin_level": "8",
        "boundary": "administrative",
        "name": "Lausanne",
        "name:br": "Lozena",
        "name:ca": "Lausana",
        "name:frp": "Losena",
        "source": "swissBOUNDARIES3D swisstopo 2011",
        "swisstopo:BEZIRKSNUM": "2225",
        "swisstopo:BFS_NUMMER": "5586",
        "swisstopo:KANTONSNUM": "22",
        "swisstopo:OBJEKTART": "Gemeindegebiet",
        "swisstopo:SHN": "CH22255586",
        "type": "boundary",
        "wikidata": "Q807",
        "wikipedia": "fr:Lausanne"
    },
    "population": 133521.0,
    "lat": 46.5218269,
    "lon": 6.6327025
}