{
    "bounds": {
        "minlat": 53.3951118,
        "minlon": 8.1053284,
        "maxlat": 54.0276817,
        "maxlon": 10.3252805
    },
    "id": 62782,
    "tags": {
        "ISO3166-2": "DE-HH",
        "TMC:cid_58:tabcd_1:Class": "Area",
        "TMC:cid_58:tabcd_1:LCLversion": "12.0",
        "TMC:cid_58:tabcd_1:LocationCode": "257",
        "admin_level": "4",
        "boundary": "administrative",
        "boundary_type": "state",
        "de:amtlicher_gemeindeschluessel": "02000000",
        "de:regionalschluessel": "020000000000",
        "is_in:state": "Bundesrepublik Deutschland",
        "name": "Hamburg",
        "name:ar": "\u0647\u0627\u0645\u0628\u0648\u0631\u063a",
        "name:de": "Hamburg",
        "name:en": "Hamburg",
        "name:eo": "Hamburgo",
        "name:fr": "Hambourg",
        "name:lv": "Hamburga",
        "name:prefix": "Freie und Hansestadt",
        "name:ru": "\u0413\u0430\u043c\u0431\u0443\u0440\u0433",
        "name:sk": "Hamburg",
        "name:sr": "\u0425\u0430\u043c\u0431\u0443\u0440\u0433",
        "name:uk": "\u0413\u0430\u043c\u0431\u0443\u0440\u0491",
        "name:zh": "\u6c49\u5821",
        "note": "Admin Level f\u00fcr Bundesland und Stadt \"Hamburg\" mit Inseln (Neuwerk(bewohnt),Scharnh\u00f6rn,Nigeh\u00f6rn)",
        "note:de": "Gebiet = Hamburg, Insel Nigeh\u00f6rn, Insel Scharh\u00f6rn",
        "official_name": "Freie und Hansestadt Hamburg",
        "official_status": "Land",
        "official_status:de": "Land",
        "official_status:en": "State",
        "official_status:ru": "\u0437\u0435\u043c\u043b\u044f",
        "ref": "HH",
        "source": "http://wiki.openstreetmap.org/wiki/Import/Catalogue/Kreisgrenzen_Deutschland_2005",
        "type": "boundary",
        "wikidata": "Q1055",
        "wikipedia": "de:Hamburg"
    },
    "population": 1812709.0,
    "lat": 53.550341,
    "lon": 10.000654
}